{
   "debugImage": "http://htmlforge.eastus.cloudapp.azure.com:8080/api/blocksdetected/getDebugImage/hdnTg_akAPF_Qpn93_1if1Z_LUjef",
   "blocks": [
      {
         "ID": 1,
         "X_Axis": 157,
         "Y_Axis": 118,
         "Width": 1595,
         "Height": 695,
         "Predictions": [
            [
               "singleImage",
               0.9985015392303467
            ]
         ],
         "Best_Predictions": [
            "singleImage",
            0.9985015392303467
         ],
         "Second_Best": [],
         "Image_Crop_Path": "http://htmlforge.eastus.cloudapp.azure.com:8080/api/blocksdetected/hdnTg_akAPF_Qpn93_1if1Z_LUjef/CropImage/1",
         "Server_Local_Image_Path": "/home/htmlforge/HTML_Forge/App/UserUpload/hdnTg_akAPF_Qpn93_1if1Z_LUjef/ImageCrops/1.png",
         "Block_Code": ""
      },
      {
         "ID": 2,
         "X_Axis": 98,
         "Y_Axis": 934,
         "Width": 1641,
         "Height": 588,
         "Predictions": [
            [
               "Title",
               0.6052614450454712
            ]
         ],
         "Best_Predictions": [
            "Title",
            0.6052614450454712
         ],
         "Second_Best": [],
         "Image_Crop_Path": "http://htmlforge.eastus.cloudapp.azure.com:8080/api/blocksdetected/hdnTg_akAPF_Qpn93_1if1Z_LUjef/CropImage/2",
         "Server_Local_Image_Path": "/home/htmlforge/HTML_Forge/App/UserUpload/hdnTg_akAPF_Qpn93_1if1Z_LUjef/ImageCrops/2.png",
         "Block_Code": ""
      },
      {
         "ID": 3,
         "X_Axis": 180,
         "Y_Axis": 1592,
         "Width": 1490,
         "Height": 436,
         "Predictions": [
            [
               "Title",
               0.9995121955871582
            ]
         ],
         "Best_Predictions": [
            "Title",
            0.9995121955871582
         ],
         "Second_Best": [],
         "Image_Crop_Path": "http://htmlforge.eastus.cloudapp.azure.com:8080/api/blocksdetected/hdnTg_akAPF_Qpn93_1if1Z_LUjef/CropImage/3",
         "Server_Local_Image_Path": "/home/htmlforge/HTML_Forge/App/UserUpload/hdnTg_akAPF_Qpn93_1if1Z_LUjef/ImageCrops/3.png",
         "Block_Code": ""
      },
      {
         "ID": 4,
         "X_Axis": 206,
         "Y_Axis": 2321,
         "Width": 1618,
         "Height": 435,
         "Predictions": [
            [
               "Header",
               0.5048192143440247
            ],
            [
               "Img_Gal_Parallax",
               0.4561156928539276
            ]
         ],
         "Best_Predictions": [
            "Header",
            0.5048192143440247
         ],
         "Second_Best": [
            "Img_Gal_Parallax",
            0.4561156928539276
         ],
         "Image_Crop_Path": "http://htmlforge.eastus.cloudapp.azure.com:8080/api/blocksdetected/hdnTg_akAPF_Qpn93_1if1Z_LUjef/CropImage/4",
         "Server_Local_Image_Path": "/home/htmlforge/HTML_Forge/App/UserUpload/hdnTg_akAPF_Qpn93_1if1Z_LUjef/ImageCrops/4.png",
         "Block_Code": ""
      }
   ]
}